pg88/__init__.py
pg88/example.py
PG88-1.0.1.dist-info/LICENSE
PG88-1.0.1.dist-info/METADATA
PG88-1.0.1.dist-info/WHEEL
PG88-1.0.1.dist-info/top_level.txt
PG88-1.0.1.dist-info/RECORD
