Metadata-Version: 2.1
Name: PG88
Version: 1.0.1
Summary: PG88 เข้าสู่ระบบเว็บสล็อตเครดิตฟรี wallet
Author-email: PG88 <PG88@example.com>
Project-URL: Homepage, https://github.com/
Classifier: Programming Language :: Python :: 3
Classifier: License :: OSI Approved :: MIT License
Classifier: Operating System :: OS Independent
Requires-Python: >=3.7
License-File: LICENSE
